merkly/__init__.py
merkly/mtree.py
merkly/node.py
merkly/utils.py
merkly-1.0.2.dist-info/LICENSE
merkly-1.0.2.dist-info/METADATA
merkly-1.0.2.dist-info/WHEEL
merkly-1.0.2.dist-info/entry_points.txt
merkly-1.0.2.dist-info/RECORD
