Metadata-Version: 2.1
Name: merkly
Version: 1.0.2
Summary: 🌳 The simple and easy implementation of Merkle Tree
Home-page: https://github.com/olivmath/merkly.git
License: MIT
Keywords: merkle-tree,merkle-proof,merkle-root,keccak256,blockchain
Author: Lucas Oliveira
Author-email: olivmath@protonmail.com
Requires-Python: >=3.8,<4.0
Classifier: Development Status :: 5 - Production/Stable
Classifier: Intended Audience :: Developers
Classifier: License :: OSI Approved :: MIT License
Classifier: Operating System :: OS Independent
Classifier: Programming Language :: Python
Classifier: Programming Language :: Python :: 3
Classifier: Programming Language :: Python :: 3.8
Classifier: Programming Language :: Python :: 3.9
Classifier: Programming Language :: Python :: 3.10
Classifier: Programming Language :: Python :: 3.11
Classifier: Programming Language :: Python :: 3.12
Classifier: Topic :: Security :: Cryptography
Classifier: Topic :: Software Development :: Libraries
Classifier: Topic :: Software Development :: Libraries :: Python Modules
Requires-Dist: pycryptodome (>=3.19.0,<4.0.0)
Requires-Dist: pydantic (>=1.10.2,<2.0.0)
Project-URL: Documentation, https://pypi.org/project/merkly/
Project-URL: Repository, https://github.com/olivmath/merkly.git
